{"entries" :
    [
        {"id":"navStart", "label": "Home", "href": "#!/home", "url": "content/aleks/html/home.html",
            "subm": []},
 
        {"id":"navTravel", "label": "Reisen", "href": "#!/trav",  "url": "content/aleks/html/reisen.html",
            "subm": [ {"label": "Detschland", "href": "#!/trav/de", "url": "content/aleks/html/De/Deutschland.html",
                        "subm": [{"label": "Landschaften", "href": "#!/trav/de/l", "url": "content/aleks/html/De/Landschaften.html"},
                         {"label": "Nordsee", "href": "#!/trav/de/n", "url": "content/aleks/html/De/Nordsee.html"},
                         {"label": "Ostsee", "href": "#!/trav/de/o", "url": "content/aleks/html/De/Ostsee.html"}]
                 },
                    {"label": "Europa", "href": "#!/trav/eu", "url": "content/aleks/html/Eu/Europa.html",
                        "subm": [{"label": "Amsterdam", "href": "#!/trav/eu/am", "url": "content/aleks/html/Eu/Amsterdam.html"},
                         {"label": "Barcelona", "href": "#!/trav/eu/ba", "url": "content/aleks/html/Eu/Barcelona.html"},
                         {"label": "Brüssel", "href": "#!/trav/eu/br", "url": "content/aleks/html/Eu/Bruessel.html"},
                         {"label": "Lissabon", "href": "#!/trav/eu/lb", "url": "content/aleks/html/Eu/Lissabon.html"},
                         {"label": "Paris", "href": "#!/trav/eu/pa", "url": "content/aleks/html/Eu/Paris.html"},
                         {"label": "Rom", "href": "#!/trav/eu/ro", "url": "content/aleks/html/Eu/Rom.html"},
                         {"label": "Tour Norwegen", "href": "#!/trav/eu/tn", "url": "content/aleks/html/Eu/Tour-Norwegen.html"},
                         {"label": "Tour Ostsee", "href": "#!/trav/eu/to", "url": "content/aleks/html/Eu/Tour-Ostsee.html"}]
                 }]},
        {"id":"navProg", "label": "Programmieren", "href": "#!/prog", "url": "content/aleks/html/prog.html",
            "subm": []},
                                           
        {"id":"navNews", "label": "News", "href": "#!/new", "url": "app/template/news/news.html", 
            "subm": [ {"label": "Archiv", "href": "#!/new/1", "url": "app/template/news/newArchiv.html"}]},
        
        {"id":"navService", "label": "Service", "href": "#!/srv", "url": "content/aleks/html/service.html",
            "subm": [ {"label": "SiteMap", "href": "#!/srv/smap", "url": "app/template/sitemap.html"}, 
                    {"label": "Cookies", "href": "#!/srv/cookies", "url": "content/aleks/html/CookiesNotRequired.html"}, 
                    {"label": "Impressum", "href": "#!/srv/imp", "url": "content/aleks/html/impressum.html"}, 
                    {"label": "Datenschutz", "href": "#!/srv/ds", "url": "content/aleks/html/datenschutz2.html"}, 
                    {"label": "Hintergrund Bilder", "href": "#!/srv/pic", "url": "content/aleks/html/srv/backGround.html"}
            ]}                                              
        
    ]
}